oklabsdk/__init__.py
oklabsdk/helpers.py
oklabsdk/llm.py
oklabsdk/oklabsdk.py
oklabsdk/version.py
oklabsdk/__pycache__/__init__.cpython-312.pyc
oklabsdk/__pycache__/helpers.cpython-312.pyc
oklabsdk/__pycache__/llm.cpython-312.pyc
oklabsdk/__pycache__/oklabsdk.cpython-312.pyc
oklabsdk/__pycache__/version.cpython-312.pyc
oklabsdk-0.0.3.dist-info/LICENSE
oklabsdk-0.0.3.dist-info/METADATA
oklabsdk-0.0.3.dist-info/WHEEL
oklabsdk-0.0.3.dist-info/top_level.txt
oklabsdk-0.0.3.dist-info/RECORD
