Metadata-Version: 2.1
Name: oklabsdk
Version: 0.0.3
Summary: OKLab Software Development Kit
Author-email: Matej Holubec <holubec@oksystem.cz>
License: GNU General Public License v3 (GPLv3)
Project-URL: url, https://oksystem.cz
Classifier: Development Status :: 4 - Beta
Classifier: Environment :: Console
Classifier: Intended Audience :: Developers
Classifier: License :: OSI Approved :: GNU General Public License v3 (GPLv3)
Classifier: Operating System :: POSIX :: Linux
Classifier: Programming Language :: Python :: 3.10
Classifier: Programming Language :: Python :: Implementation :: PyPy
Classifier: Topic :: Software Development :: Libraries :: Python Modules
Requires-Python: >=3.10
License-File: LICENSE
Requires-Dist: python-dotenv
Requires-Dist: requests
Requires-Dist: pdf2image
